MANIFEST.in
README.rst
nose_exclude.py
setup.py
tests.py
tox.ini
nose_exclude.egg-info/PKG-INFO
nose_exclude.egg-info/SOURCES.txt
nose_exclude.egg-info/dependency_links.txt
nose_exclude.egg-info/entry_points.txt
nose_exclude.egg-info/not-zip-safe
nose_exclude.egg-info/requires.txt
nose_exclude.egg-info/top_level.txt
test_dirs/exclude_dirs.txt
test_dirs/exclude_dirs2.txt
test_dirs/build/test.py
test_dirs/build2/tests.py
test_dirs/fish/tests.py
test_dirs/test_not_me/test.py
test_dirs/test_yes/tests.py
test_dirs/test_yes2/tests.py