Metadata-Version: 1.1
Name: nose-exclude
Version: 0.1.10
Summary: Exclude specific directories from nosetests runs.
Home-page: http://bitbucket.org/kgrandis/nose-exclude
Author: Kurt Grandis
Author-email: kgrandis@gmail.com
License: GNU LGPL
Platform: UNKNOWN
Classifier: Development Status :: 3 - Alpha
Classifier: Intended Audience :: Developers
Classifier: License :: OSI Approved :: GNU Library or Lesser General Public License (LGPL)
Classifier: Topic :: Software Development :: Testing
Classifier: Programming Language :: Python
